arneso_ctest_py.libs/libbrotlicommon-24c3c480.so.1.0.9
arneso_ctest_py.libs/libbrotlidec-11aaeb4b.so.1.0.9
arneso_ctest_py.libs/libcom_err-c28b3a5a.so.2.1
arneso_ctest_py.libs/libcrypt-1e9ce68f.so.2.0.0
arneso_ctest_py.libs/libcrypto-1dce7ec2.so.3.5.1
arneso_ctest_py.libs/libcurl-74c9fd7e.so.4.7.0
arneso_ctest_py.libs/libevent-2-bb9471ec.1.so.7.0.1
arneso_ctest_py.libs/libgssapi_krb5-82e569d3.so.2.2
arneso_ctest_py.libs/libidn2-5237fb84.so.0.3.7
arneso_ctest_py.libs/libk5crypto-188823b6.so.3.1
arneso_ctest_py.libs/libkeyutils-81e5c457.so.1.10
arneso_ctest_py.libs/libkrb5-68b134bf.so.3.3
arneso_ctest_py.libs/libkrb5support-28787768.so.0.1
arneso_ctest_py.libs/liblber-63bca5a9.so.2.0.200
arneso_ctest_py.libs/libldap_r-4d1c9e88.so.2.0.200
arneso_ctest_py.libs/libnghttp2-25a83100.so.14.20.1
arneso_ctest_py.libs/libpcre2-8-b77f698a.so.0.11.0
arneso_ctest_py.libs/libpsl-5e17ba32.so.5.3.3
arneso_ctest_py.libs/libsasl2-6b2d3aab.so.3.0.0
arneso_ctest_py.libs/libselinux-a1ff09bf.so.1
arneso_ctest_py.libs/libssh-5de6c0e8.so.4.9.4
arneso_ctest_py.libs/libssl-e892a39c.so.3.5.1
arneso_ctest_py.libs/libunistring-7ed7589d.so.2.1.0
ctest_py/__init__.py
ctest_py/__main__.py
ctest_py/_build_cffi.py
ctest_py/_curlcrypto.cpython-313-x86_64-linux-gnu.so
ctest_py/functions.py
ctest_py/libcloudsqlite.so
ctest_py/plugin.py
ctest_py/py.typed
arneso_ctest_py-0.2.0.dist-info/METADATA
arneso_ctest_py-0.2.0.dist-info/WHEEL
arneso_ctest_py-0.2.0.dist-info/entry_points.txt
arneso_ctest_py-0.2.0.dist-info/RECORD
arneso_ctest_py-0.2.0.dist-info/licenses/LICENSE
arneso_ctest_py-0.2.0.dist-info/sboms/auditwheel.cdx.json
