Metadata-Version: 2.4
Name: arneso-ctest-py
Version: 0.2.0
Summary: CTest Py
Author-Email: =?utf-8?q?Arne_S=C3=B8rli?= <arne.sorli@ssb.no>
License-Expression: MIT
Project-URL: homepage, https://github.com/arneso-ssb/ctest-py
Project-URL: repository, https://github.com/arneso-ssb/ctest-py
Project-URL: documentation, https://arneso-ssb.github.io/ctest-py
Project-URL: Changelog, https://github.com/arneso-ssb/ctest-py/releases
Requires-Python: <4.0,>=3.10
Requires-Dist: click>=8.0.1
Requires-Dist: setuptools>=80.9.0
Requires-Dist: cffi<2.0.0,>=1.17.0
Requires-Dist: google-auth>=2.43.0
